krules_env/__init__.py
krules_env/env.py
krules_env/settings_loader.py
krules_env/tests/__init__.py
krules_env/tests/test_procevent_filtered.py
krules_env-0.12.0.dist-info/AUTHORS
krules_env-0.12.0.dist-info/LICENSE
krules_env-0.12.0.dist-info/METADATA
krules_env-0.12.0.dist-info/WHEEL
krules_env-0.12.0.dist-info/RECORD
