Metadata-Version: 2.1
Name: krules-env
Version: 0.12.0
Summary: KRules environment base package
Home-page: https://github.com/airspot-dev/krules
License: Apache Licence 2.0
Author: Alberto Degli Esposti
Author-email: alberto@arispot.tech
Requires-Python: >=3.11,<3.12
Classifier: Development Status :: 3 - Alpha
Classifier: License :: OSI Approved :: Apache Software License
Classifier: License :: Other/Proprietary License
Classifier: Programming Language :: Python :: 3
Classifier: Programming Language :: Python :: 3.11
Requires-Dist: PyYAML (>=6.0.1)
Requires-Dist: krules-dispatcher-cloudevents (>=0.12.0,<0.13.0)
Project-URL: Repository, https://github.com/airspot-dev/krules
